[
  {
    "id": 537327,
    "matchday": 1,
    "round": "GROUP_A",
    "date": "2026-06-11T19:00:00Z",
    "homeTeam": "MEX",
    "homeTeamName": "Mexico",
    "awayTeam": "RSA",
    "awayTeamName": "South Africa",
    "homeGoals": 2,
    "awayGoals": 0,
    "status": "FINISHED"
  },
  {
    "id": 537328,
    "matchday": 1,
    "round": "GROUP_A",
    "date": "2026-06-12T02:00:00Z",
    "homeTeam": "KOR",
    "homeTeamName": "South Korea",
    "awayTeam": "CZE",
    "awayTeamName": "Czechia",
    "homeGoals": 2,
    "awayGoals": 1,
    "status": "FINISHED"
  },
  {
    "id": 537329,
    "matchday": 2,
    "round": "GROUP_A",
    "date": "2026-06-18T16:00:00Z",
    "homeTeam": "CZE",
    "homeTeamName": "Czechia",
    "awayTeam": "RSA",
    "awayTeamName": "South Africa",
    "homeGoals": 1,
    "awayGoals": 1,
    "status": "FINISHED"
  },
  {
    "id": 537330,
    "matchday": 2,
    "round": "GROUP_A",
    "date": "2026-06-19T01:00:00Z",
    "homeTeam": "MEX",
    "homeTeamName": "Mexico",
    "awayTeam": "KOR",
    "awayTeamName": "South Korea",
    "homeGoals": 1,
    "awayGoals": 0,
    "status": "FINISHED"
  },
  {
    "id": 537331,
    "matchday": 3,
    "round": "GROUP_A",
    "date": "2026-06-25T01:00:00Z",
    "homeTeam": "CZE",
    "homeTeamName": "Czechia",
    "awayTeam": "MEX",
    "awayTeamName": "Mexico",
    "homeGoals": null,
    "awayGoals": null,
    "status": "TIMED"
  },
  {
    "id": 537332,
    "matchday": 3,
    "round": "GROUP_A",
    "date": "2026-06-25T01:00:00Z",
    "homeTeam": "RSA",
    "homeTeamName": "South Africa",
    "awayTeam": "KOR",
    "awayTeamName": "South Korea",
    "homeGoals": null,
    "awayGoals": null,
    "status": "TIMED"
  },
  {
    "id": 537333,
    "matchday": 1,
    "round": "GROUP_B",
    "date": "2026-06-12T19:00:00Z",
    "homeTeam": "CAN",
    "homeTeamName": "Canada",
    "awayTeam": "BIH",
    "awayTeamName": "Bosnia-Herzegovina",
    "homeGoals": 1,
    "awayGoals": 1,
    "status": "FINISHED"
  },
  {
    "id": 537334,
    "matchday": 1,
    "round": "GROUP_B",
    "date": "2026-06-13T19:00:00Z",
    "homeTeam": "QAT",
    "homeTeamName": "Qatar",
    "awayTeam": "SUI",
    "awayTeamName": "Switzerland",
    "homeGoals": 1,
    "awayGoals": 1,
    "status": "FINISHED"
  },
  {
    "id": 537335,
    "matchday": 2,
    "round": "GROUP_B",
    "date": "2026-06-18T19:00:00Z",
    "homeTeam": "SUI",
    "homeTeamName": "Switzerland",
    "awayTeam": "BIH",
    "awayTeamName": "Bosnia-Herzegovina",
    "homeGoals": 4,
    "awayGoals": 1,
    "status": "FINISHED"
  },
  {
    "id": 537336,
    "matchday": 2,
    "round": "GROUP_B",
    "date": "2026-06-18T22:00:00Z",
    "homeTeam": "CAN",
    "homeTeamName": "Canada",
    "awayTeam": "QAT",
    "awayTeamName": "Qatar",
    "homeGoals": 6,
    "awayGoals": 0,
    "status": "FINISHED"
  },
  {
    "id": 537337,
    "matchday": 3,
    "round": "GROUP_B",
    "date": "2026-06-24T19:00:00Z",
    "homeTeam": "SUI",
    "homeTeamName": "Switzerland",
    "awayTeam": "CAN",
    "awayTeamName": "Canada",
    "homeGoals": null,
    "awayGoals": null,
    "status": "TIMED"
  },
  {
    "id": 537338,
    "matchday": 3,
    "round": "GROUP_B",
    "date": "2026-06-24T19:00:00Z",
    "homeTeam": "BIH",
    "homeTeamName": "Bosnia-Herzegovina",
    "awayTeam": "QAT",
    "awayTeamName": "Qatar",
    "homeGoals": null,
    "awayGoals": null,
    "status": "TIMED"
  },
  {
    "id": 537339,
    "matchday": 1,
    "round": "GROUP_C",
    "date": "2026-06-13T22:00:00Z",
    "homeTeam": "BRA",
    "homeTeamName": "Brazil",
    "awayTeam": "MAR",
    "awayTeamName": "Morocco",
    "homeGoals": 1,
    "awayGoals": 1,
    "status": "FINISHED"
  },
  {
    "id": 537340,
    "matchday": 1,
    "round": "GROUP_C",
    "date": "2026-06-14T01:00:00Z",
    "homeTeam": "HAI",
    "homeTeamName": "Haiti",
    "awayTeam": "SCO",
    "awayTeamName": "Scotland",
    "homeGoals": 0,
    "awayGoals": 1,
    "status": "FINISHED"
  },
  {
    "id": 537341,
    "matchday": 2,
    "round": "GROUP_C",
    "date": "2026-06-20T00:30:00Z",
    "homeTeam": "BRA",
    "homeTeamName": "Brazil",
    "awayTeam": "HAI",
    "awayTeamName": "Haiti",
    "homeGoals": 3,
    "awayGoals": 0,
    "status": "FINISHED"
  },
  {
    "id": 537342,
    "matchday": 2,
    "round": "GROUP_C",
    "date": "2026-06-19T22:00:00Z",
    "homeTeam": "SCO",
    "homeTeamName": "Scotland",
    "awayTeam": "MAR",
    "awayTeamName": "Morocco",
    "homeGoals": 0,
    "awayGoals": 1,
    "status": "FINISHED"
  },
  {
    "id": 537343,
    "matchday": 3,
    "round": "GROUP_C",
    "date": "2026-06-24T22:00:00Z",
    "homeTeam": "SCO",
    "homeTeamName": "Scotland",
    "awayTeam": "BRA",
    "awayTeamName": "Brazil",
    "homeGoals": null,
    "awayGoals": null,
    "status": "TIMED"
  },
  {
    "id": 537344,
    "matchday": 3,
    "round": "GROUP_C",
    "date": "2026-06-24T22:00:00Z",
    "homeTeam": "MAR",
    "homeTeamName": "Morocco",
    "awayTeam": "HAI",
    "awayTeamName": "Haiti",
    "homeGoals": null,
    "awayGoals": null,
    "status": "TIMED"
  },
  {
    "id": 537345,
    "matchday": 1,
    "round": "GROUP_D",
    "date": "2026-06-13T01:00:00Z",
    "homeTeam": "USA",
    "homeTeamName": "United States",
    "awayTeam": "PAR",
    "awayTeamName": "Paraguay",
    "homeGoals": 4,
    "awayGoals": 1,
    "status": "FINISHED"
  },
  {
    "id": 537346,
    "matchday": 1,
    "round": "GROUP_D",
    "date": "2026-06-14T04:00:00Z",
    "homeTeam": "AUS",
    "homeTeamName": "Australia",
    "awayTeam": "TUR",
    "awayTeamName": "Turkey",
    "homeGoals": 2,
    "awayGoals": 0,
    "status": "FINISHED"
  },
  {
    "id": 537347,
    "matchday": 2,
    "round": "GROUP_D",
    "date": "2026-06-20T03:00:00Z",
    "homeTeam": "TUR",
    "homeTeamName": "Turkey",
    "awayTeam": "PAR",
    "awayTeamName": "Paraguay",
    "homeGoals": 0,
    "awayGoals": 1,
    "status": "FINISHED"
  },
  {
    "id": 537348,
    "matchday": 2,
    "round": "GROUP_D",
    "date": "2026-06-19T19:00:00Z",
    "homeTeam": "USA",
    "homeTeamName": "United States",
    "awayTeam": "AUS",
    "awayTeamName": "Australia",
    "homeGoals": 2,
    "awayGoals": 0,
    "status": "FINISHED"
  },
  {
    "id": 537349,
    "matchday": 3,
    "round": "GROUP_D",
    "date": "2026-06-26T02:00:00Z",
    "homeTeam": "TUR",
    "homeTeamName": "Turkey",
    "awayTeam": "USA",
    "awayTeamName": "United States",
    "homeGoals": null,
    "awayGoals": null,
    "status": "TIMED"
  },
  {
    "id": 537350,
    "matchday": 3,
    "round": "GROUP_D",
    "date": "2026-06-26T02:00:00Z",
    "homeTeam": "PAR",
    "homeTeamName": "Paraguay",
    "awayTeam": "AUS",
    "awayTeamName": "Australia",
    "homeGoals": null,
    "awayGoals": null,
    "status": "TIMED"
  },
  {
    "id": 537351,
    "matchday": 1,
    "round": "GROUP_E",
    "date": "2026-06-14T17:00:00Z",
    "homeTeam": "GER",
    "homeTeamName": "Germany",
    "awayTeam": "CUW",
    "awayTeamName": "Cura\u00e7ao",
    "homeGoals": 7,
    "awayGoals": 1,
    "status": "FINISHED"
  },
  {
    "id": 537352,
    "matchday": 1,
    "round": "GROUP_E",
    "date": "2026-06-14T23:00:00Z",
    "homeTeam": "CIV",
    "homeTeamName": "Ivory Coast",
    "awayTeam": "ECU",
    "awayTeamName": "Ecuador",
    "homeGoals": 1,
    "awayGoals": 0,
    "status": "FINISHED"
  },
  {
    "id": 537353,
    "matchday": 2,
    "round": "GROUP_E",
    "date": "2026-06-20T20:00:00Z",
    "homeTeam": "GER",
    "homeTeamName": "Germany",
    "awayTeam": "CIV",
    "awayTeamName": "Ivory Coast",
    "homeGoals": 2,
    "awayGoals": 1,
    "status": "FINISHED"
  },
  {
    "id": 537354,
    "matchday": 2,
    "round": "GROUP_E",
    "date": "2026-06-21T00:00:00Z",
    "homeTeam": "ECU",
    "homeTeamName": "Ecuador",
    "awayTeam": "CUW",
    "awayTeamName": "Cura\u00e7ao",
    "homeGoals": 0,
    "awayGoals": 0,
    "status": "FINISHED"
  },
  {
    "id": 537355,
    "matchday": 3,
    "round": "GROUP_E",
    "date": "2026-06-25T20:00:00Z",
    "homeTeam": "ECU",
    "homeTeamName": "Ecuador",
    "awayTeam": "GER",
    "awayTeamName": "Germany",
    "homeGoals": null,
    "awayGoals": null,
    "status": "TIMED"
  },
  {
    "id": 537356,
    "matchday": 3,
    "round": "GROUP_E",
    "date": "2026-06-25T20:00:00Z",
    "homeTeam": "CUW",
    "homeTeamName": "Cura\u00e7ao",
    "awayTeam": "CIV",
    "awayTeamName": "Ivory Coast",
    "homeGoals": null,
    "awayGoals": null,
    "status": "TIMED"
  },
  {
    "id": 537357,
    "matchday": 1,
    "round": "GROUP_F",
    "date": "2026-06-14T20:00:00Z",
    "homeTeam": "NED",
    "homeTeamName": "Netherlands",
    "awayTeam": "JPN",
    "awayTeamName": "Japan",
    "homeGoals": 2,
    "awayGoals": 2,
    "status": "FINISHED"
  },
  {
    "id": 537358,
    "matchday": 1,
    "round": "GROUP_F",
    "date": "2026-06-15T02:00:00Z",
    "homeTeam": "SWE",
    "homeTeamName": "Sweden",
    "awayTeam": "TUN",
    "awayTeamName": "Tunisia",
    "homeGoals": 5,
    "awayGoals": 1,
    "status": "FINISHED"
  },
  {
    "id": 537359,
    "matchday": 2,
    "round": "GROUP_F",
    "date": "2026-06-20T17:00:00Z",
    "homeTeam": "NED",
    "homeTeamName": "Netherlands",
    "awayTeam": "SWE",
    "awayTeamName": "Sweden",
    "homeGoals": 5,
    "awayGoals": 1,
    "status": "FINISHED"
  },
  {
    "id": 537360,
    "matchday": 2,
    "round": "GROUP_F",
    "date": "2026-06-21T04:00:00Z",
    "homeTeam": "TUN",
    "homeTeamName": "Tunisia",
    "awayTeam": "JPN",
    "awayTeamName": "Japan",
    "homeGoals": 0,
    "awayGoals": 4,
    "status": "FINISHED"
  },
  {
    "id": 537361,
    "matchday": 3,
    "round": "GROUP_F",
    "date": "2026-06-25T23:00:00Z",
    "homeTeam": "TUN",
    "homeTeamName": "Tunisia",
    "awayTeam": "NED",
    "awayTeamName": "Netherlands",
    "homeGoals": null,
    "awayGoals": null,
    "status": "TIMED"
  },
  {
    "id": 537362,
    "matchday": 3,
    "round": "GROUP_F",
    "date": "2026-06-25T23:00:00Z",
    "homeTeam": "JPN",
    "homeTeamName": "Japan",
    "awayTeam": "SWE",
    "awayTeamName": "Sweden",
    "homeGoals": null,
    "awayGoals": null,
    "status": "TIMED"
  },
  {
    "id": 537363,
    "matchday": 1,
    "round": "GROUP_G",
    "date": "2026-06-15T19:00:00Z",
    "homeTeam": "BEL",
    "homeTeamName": "Belgium",
    "awayTeam": "EGY",
    "awayTeamName": "Egypt",
    "homeGoals": 1,
    "awayGoals": 1,
    "status": "FINISHED"
  },
  {
    "id": 537364,
    "matchday": 1,
    "round": "GROUP_G",
    "date": "2026-06-16T01:00:00Z",
    "homeTeam": "IRN",
    "homeTeamName": "Iran",
    "awayTeam": "NZL",
    "awayTeamName": "New Zealand",
    "homeGoals": 2,
    "awayGoals": 2,
    "status": "FINISHED"
  },
  {
    "id": 537365,
    "matchday": 2,
    "round": "GROUP_G",
    "date": "2026-06-21T19:00:00Z",
    "homeTeam": "BEL",
    "homeTeamName": "Belgium",
    "awayTeam": "IRN",
    "awayTeamName": "Iran",
    "homeGoals": null,
    "awayGoals": null,
    "status": "TIMED"
  },
  {
    "id": 537366,
    "matchday": 2,
    "round": "GROUP_G",
    "date": "2026-06-22T01:00:00Z",
    "homeTeam": "NZL",
    "homeTeamName": "New Zealand",
    "awayTeam": "EGY",
    "awayTeamName": "Egypt",
    "homeGoals": null,
    "awayGoals": null,
    "status": "TIMED"
  },
  {
    "id": 537367,
    "matchday": 3,
    "round": "GROUP_G",
    "date": "2026-06-27T03:00:00Z",
    "homeTeam": "NZL",
    "homeTeamName": "New Zealand",
    "awayTeam": "BEL",
    "awayTeamName": "Belgium",
    "homeGoals": null,
    "awayGoals": null,
    "status": "TIMED"
  },
  {
    "id": 537368,
    "matchday": 3,
    "round": "GROUP_G",
    "date": "2026-06-27T03:00:00Z",
    "homeTeam": "EGY",
    "homeTeamName": "Egypt",
    "awayTeam": "IRN",
    "awayTeamName": "Iran",
    "homeGoals": null,
    "awayGoals": null,
    "status": "TIMED"
  },
  {
    "id": 537369,
    "matchday": 1,
    "round": "GROUP_H",
    "date": "2026-06-15T16:00:00Z",
    "homeTeam": "ESP",
    "homeTeamName": "Spain",
    "awayTeam": "CPV",
    "awayTeamName": "Cape Verde Islands",
    "homeGoals": 0,
    "awayGoals": 0,
    "status": "FINISHED"
  },
  {
    "id": 537370,
    "matchday": 1,
    "round": "GROUP_H",
    "date": "2026-06-15T22:00:00Z",
    "homeTeam": "KSA",
    "homeTeamName": "Saudi Arabia",
    "awayTeam": "URU",
    "awayTeamName": "Uruguay",
    "homeGoals": 1,
    "awayGoals": 1,
    "status": "FINISHED"
  },
  {
    "id": 537371,
    "matchday": 2,
    "round": "GROUP_H",
    "date": "2026-06-21T16:00:00Z",
    "homeTeam": "ESP",
    "homeTeamName": "Spain",
    "awayTeam": "KSA",
    "awayTeamName": "Saudi Arabia",
    "homeGoals": null,
    "awayGoals": null,
    "status": "TIMED"
  },
  {
    "id": 537372,
    "matchday": 2,
    "round": "GROUP_H",
    "date": "2026-06-21T22:00:00Z",
    "homeTeam": "URU",
    "homeTeamName": "Uruguay",
    "awayTeam": "CPV",
    "awayTeamName": "Cape Verde Islands",
    "homeGoals": null,
    "awayGoals": null,
    "status": "TIMED"
  },
  {
    "id": 537373,
    "matchday": 3,
    "round": "GROUP_H",
    "date": "2026-06-27T00:00:00Z",
    "homeTeam": "URU",
    "homeTeamName": "Uruguay",
    "awayTeam": "ESP",
    "awayTeamName": "Spain",
    "homeGoals": null,
    "awayGoals": null,
    "status": "TIMED"
  },
  {
    "id": 537374,
    "matchday": 3,
    "round": "GROUP_H",
    "date": "2026-06-27T00:00:00Z",
    "homeTeam": "CPV",
    "homeTeamName": "Cape Verde Islands",
    "awayTeam": "KSA",
    "awayTeamName": "Saudi Arabia",
    "homeGoals": null,
    "awayGoals": null,
    "status": "TIMED"
  },
  {
    "id": 537391,
    "matchday": 1,
    "round": "GROUP_I",
    "date": "2026-06-16T19:00:00Z",
    "homeTeam": "FRA",
    "homeTeamName": "France",
    "awayTeam": "SEN",
    "awayTeamName": "Senegal",
    "homeGoals": 3,
    "awayGoals": 1,
    "status": "FINISHED"
  },
  {
    "id": 537392,
    "matchday": 1,
    "round": "GROUP_I",
    "date": "2026-06-16T22:00:00Z",
    "homeTeam": "IRQ",
    "homeTeamName": "Iraq",
    "awayTeam": "NOR",
    "awayTeamName": "Norway",
    "homeGoals": 1,
    "awayGoals": 4,
    "status": "FINISHED"
  },
  {
    "id": 537393,
    "matchday": 2,
    "round": "GROUP_I",
    "date": "2026-06-22T21:00:00Z",
    "homeTeam": "FRA",
    "homeTeamName": "France",
    "awayTeam": "IRQ",
    "awayTeamName": "Iraq",
    "homeGoals": null,
    "awayGoals": null,
    "status": "TIMED"
  },
  {
    "id": 537394,
    "matchday": 2,
    "round": "GROUP_I",
    "date": "2026-06-23T00:00:00Z",
    "homeTeam": "NOR",
    "homeTeamName": "Norway",
    "awayTeam": "SEN",
    "awayTeamName": "Senegal",
    "homeGoals": null,
    "awayGoals": null,
    "status": "TIMED"
  },
  {
    "id": 537395,
    "matchday": 3,
    "round": "GROUP_I",
    "date": "2026-06-26T19:00:00Z",
    "homeTeam": "NOR",
    "homeTeamName": "Norway",
    "awayTeam": "FRA",
    "awayTeamName": "France",
    "homeGoals": null,
    "awayGoals": null,
    "status": "TIMED"
  },
  {
    "id": 537396,
    "matchday": 3,
    "round": "GROUP_I",
    "date": "2026-06-26T19:00:00Z",
    "homeTeam": "SEN",
    "homeTeamName": "Senegal",
    "awayTeam": "IRQ",
    "awayTeamName": "Iraq",
    "homeGoals": null,
    "awayGoals": null,
    "status": "TIMED"
  },
  {
    "id": 537397,
    "matchday": 1,
    "round": "GROUP_J",
    "date": "2026-06-17T01:00:00Z",
    "homeTeam": "ARG",
    "homeTeamName": "Argentina",
    "awayTeam": "ALG",
    "awayTeamName": "Algeria",
    "homeGoals": 3,
    "awayGoals": 0,
    "status": "FINISHED"
  },
  {
    "id": 537398,
    "matchday": 1,
    "round": "GROUP_J",
    "date": "2026-06-17T04:00:00Z",
    "homeTeam": "AUT",
    "homeTeamName": "Austria",
    "awayTeam": "JOR",
    "awayTeamName": "Jordan",
    "homeGoals": 3,
    "awayGoals": 1,
    "status": "FINISHED"
  },
  {
    "id": 537399,
    "matchday": 2,
    "round": "GROUP_J",
    "date": "2026-06-22T17:00:00Z",
    "homeTeam": "ARG",
    "homeTeamName": "Argentina",
    "awayTeam": "AUT",
    "awayTeamName": "Austria",
    "homeGoals": null,
    "awayGoals": null,
    "status": "TIMED"
  },
  {
    "id": 537400,
    "matchday": 2,
    "round": "GROUP_J",
    "date": "2026-06-23T03:00:00Z",
    "homeTeam": "JOR",
    "homeTeamName": "Jordan",
    "awayTeam": "ALG",
    "awayTeamName": "Algeria",
    "homeGoals": null,
    "awayGoals": null,
    "status": "TIMED"
  },
  {
    "id": 537401,
    "matchday": 3,
    "round": "GROUP_J",
    "date": "2026-06-28T02:00:00Z",
    "homeTeam": "JOR",
    "homeTeamName": "Jordan",
    "awayTeam": "ARG",
    "awayTeamName": "Argentina",
    "homeGoals": null,
    "awayGoals": null,
    "status": "TIMED"
  },
  {
    "id": 537402,
    "matchday": 3,
    "round": "GROUP_J",
    "date": "2026-06-28T02:00:00Z",
    "homeTeam": "ALG",
    "homeTeamName": "Algeria",
    "awayTeam": "AUT",
    "awayTeamName": "Austria",
    "homeGoals": null,
    "awayGoals": null,
    "status": "TIMED"
  },
  {
    "id": 537403,
    "matchday": 1,
    "round": "GROUP_K",
    "date": "2026-06-17T17:00:00Z",
    "homeTeam": "POR",
    "homeTeamName": "Portugal",
    "awayTeam": "COD",
    "awayTeamName": "Congo DR",
    "homeGoals": 1,
    "awayGoals": 1,
    "status": "FINISHED"
  },
  {
    "id": 537404,
    "matchday": 1,
    "round": "GROUP_K",
    "date": "2026-06-18T02:00:00Z",
    "homeTeam": "UZB",
    "homeTeamName": "Uzbekistan",
    "awayTeam": "COL",
    "awayTeamName": "Colombia",
    "homeGoals": 1,
    "awayGoals": 3,
    "status": "FINISHED"
  },
  {
    "id": 537405,
    "matchday": 2,
    "round": "GROUP_K",
    "date": "2026-06-23T17:00:00Z",
    "homeTeam": "POR",
    "homeTeamName": "Portugal",
    "awayTeam": "UZB",
    "awayTeamName": "Uzbekistan",
    "homeGoals": null,
    "awayGoals": null,
    "status": "TIMED"
  },
  {
    "id": 537406,
    "matchday": 2,
    "round": "GROUP_K",
    "date": "2026-06-24T02:00:00Z",
    "homeTeam": "COL",
    "homeTeamName": "Colombia",
    "awayTeam": "COD",
    "awayTeamName": "Congo DR",
    "homeGoals": null,
    "awayGoals": null,
    "status": "TIMED"
  },
  {
    "id": 537407,
    "matchday": 3,
    "round": "GROUP_K",
    "date": "2026-06-27T23:30:00Z",
    "homeTeam": "COL",
    "homeTeamName": "Colombia",
    "awayTeam": "POR",
    "awayTeamName": "Portugal",
    "homeGoals": null,
    "awayGoals": null,
    "status": "TIMED"
  },
  {
    "id": 537408,
    "matchday": 3,
    "round": "GROUP_K",
    "date": "2026-06-27T23:30:00Z",
    "homeTeam": "COD",
    "homeTeamName": "Congo DR",
    "awayTeam": "UZB",
    "awayTeamName": "Uzbekistan",
    "homeGoals": null,
    "awayGoals": null,
    "status": "TIMED"
  },
  {
    "id": 537409,
    "matchday": 1,
    "round": "GROUP_L",
    "date": "2026-06-17T20:00:00Z",
    "homeTeam": "ENG",
    "homeTeamName": "England",
    "awayTeam": "CRO",
    "awayTeamName": "Croatia",
    "homeGoals": 4,
    "awayGoals": 2,
    "status": "FINISHED"
  },
  {
    "id": 537410,
    "matchday": 1,
    "round": "GROUP_L",
    "date": "2026-06-17T23:00:00Z",
    "homeTeam": "GHA",
    "homeTeamName": "Ghana",
    "awayTeam": "PAN",
    "awayTeamName": "Panama",
    "homeGoals": 1,
    "awayGoals": 0,
    "status": "FINISHED"
  },
  {
    "id": 537411,
    "matchday": 2,
    "round": "GROUP_L",
    "date": "2026-06-23T20:00:00Z",
    "homeTeam": "ENG",
    "homeTeamName": "England",
    "awayTeam": "GHA",
    "awayTeamName": "Ghana",
    "homeGoals": null,
    "awayGoals": null,
    "status": "TIMED"
  },
  {
    "id": 537412,
    "matchday": 2,
    "round": "GROUP_L",
    "date": "2026-06-23T23:00:00Z",
    "homeTeam": "PAN",
    "homeTeamName": "Panama",
    "awayTeam": "CRO",
    "awayTeamName": "Croatia",
    "homeGoals": null,
    "awayGoals": null,
    "status": "TIMED"
  },
  {
    "id": 537413,
    "matchday": 3,
    "round": "GROUP_L",
    "date": "2026-06-27T21:00:00Z",
    "homeTeam": "PAN",
    "homeTeamName": "Panama",
    "awayTeam": "ENG",
    "awayTeamName": "England",
    "homeGoals": null,
    "awayGoals": null,
    "status": "TIMED"
  },
  {
    "id": 537414,
    "matchday": 3,
    "round": "GROUP_L",
    "date": "2026-06-27T21:00:00Z",
    "homeTeam": "CRO",
    "homeTeamName": "Croatia",
    "awayTeam": "GHA",
    "awayTeamName": "Ghana",
    "homeGoals": null,
    "awayGoals": null,
    "status": "TIMED"
  },
  {
    "id": 537415,
    "matchday": null,
    "round": "LAST_32",
    "date": "2026-06-29T20:30:00Z",
    "homeTeam": null,
    "homeTeamName": null,
    "awayTeam": null,
    "awayTeamName": null,
    "homeGoals": null,
    "awayGoals": null,
    "status": "TIMED"
  },
  {
    "id": 537416,
    "matchday": null,
    "round": "LAST_32",
    "date": "2026-06-30T21:00:00Z",
    "homeTeam": null,
    "homeTeamName": null,
    "awayTeam": null,
    "awayTeamName": null,
    "homeGoals": null,
    "awayGoals": null,
    "status": "TIMED"
  },
  {
    "id": 537417,
    "matchday": null,
    "round": "LAST_32",
    "date": "2026-06-28T19:00:00Z",
    "homeTeam": null,
    "homeTeamName": null,
    "awayTeam": null,
    "awayTeamName": null,
    "homeGoals": null,
    "awayGoals": null,
    "status": "TIMED"
  },
  {
    "id": 537418,
    "matchday": null,
    "round": "LAST_32",
    "date": "2026-06-30T01:00:00Z",
    "homeTeam": null,
    "homeTeamName": null,
    "awayTeam": null,
    "awayTeamName": null,
    "homeGoals": null,
    "awayGoals": null,
    "status": "TIMED"
  },
  {
    "id": 537419,
    "matchday": null,
    "round": "LAST_32",
    "date": "2026-07-02T23:00:00Z",
    "homeTeam": null,
    "homeTeamName": null,
    "awayTeam": null,
    "awayTeamName": null,
    "homeGoals": null,
    "awayGoals": null,
    "status": "TIMED"
  },
  {
    "id": 537420,
    "matchday": null,
    "round": "LAST_32",
    "date": "2026-07-02T19:00:00Z",
    "homeTeam": null,
    "homeTeamName": null,
    "awayTeam": null,
    "awayTeamName": null,
    "homeGoals": null,
    "awayGoals": null,
    "status": "TIMED"
  },
  {
    "id": 537421,
    "matchday": null,
    "round": "LAST_32",
    "date": "2026-07-02T00:00:00Z",
    "homeTeam": null,
    "homeTeamName": null,
    "awayTeam": null,
    "awayTeamName": null,
    "homeGoals": null,
    "awayGoals": null,
    "status": "TIMED"
  },
  {
    "id": 537422,
    "matchday": null,
    "round": "LAST_32",
    "date": "2026-07-01T20:00:00Z",
    "homeTeam": null,
    "homeTeamName": null,
    "awayTeam": null,
    "awayTeamName": null,
    "homeGoals": null,
    "awayGoals": null,
    "status": "TIMED"
  },
  {
    "id": 537423,
    "matchday": null,
    "round": "LAST_32",
    "date": "2026-06-29T17:00:00Z",
    "homeTeam": null,
    "homeTeamName": null,
    "awayTeam": null,
    "awayTeamName": null,
    "homeGoals": null,
    "awayGoals": null,
    "status": "TIMED"
  },
  {
    "id": 537424,
    "matchday": null,
    "round": "LAST_32",
    "date": "2026-06-30T17:00:00Z",
    "homeTeam": null,
    "homeTeamName": null,
    "awayTeam": null,
    "awayTeamName": null,
    "homeGoals": null,
    "awayGoals": null,
    "status": "TIMED"
  },
  {
    "id": 537425,
    "matchday": null,
    "round": "LAST_32",
    "date": "2026-07-01T01:00:00Z",
    "homeTeam": null,
    "homeTeamName": null,
    "awayTeam": null,
    "awayTeamName": null,
    "homeGoals": null,
    "awayGoals": null,
    "status": "TIMED"
  },
  {
    "id": 537426,
    "matchday": null,
    "round": "LAST_32",
    "date": "2026-07-01T16:00:00Z",
    "homeTeam": null,
    "homeTeamName": null,
    "awayTeam": null,
    "awayTeamName": null,
    "homeGoals": null,
    "awayGoals": null,
    "status": "TIMED"
  },
  {
    "id": 537427,
    "matchday": null,
    "round": "LAST_32",
    "date": "2026-07-03T22:00:00Z",
    "homeTeam": null,
    "homeTeamName": null,
    "awayTeam": null,
    "awayTeamName": null,
    "homeGoals": null,
    "awayGoals": null,
    "status": "TIMED"
  },
  {
    "id": 537428,
    "matchday": null,
    "round": "LAST_32",
    "date": "2026-07-03T18:00:00Z",
    "homeTeam": null,
    "homeTeamName": null,
    "awayTeam": null,
    "awayTeamName": null,
    "homeGoals": null,
    "awayGoals": null,
    "status": "TIMED"
  },
  {
    "id": 537429,
    "matchday": null,
    "round": "LAST_32",
    "date": "2026-07-03T03:00:00Z",
    "homeTeam": null,
    "homeTeamName": null,
    "awayTeam": null,
    "awayTeamName": null,
    "homeGoals": null,
    "awayGoals": null,
    "status": "TIMED"
  },
  {
    "id": 537430,
    "matchday": null,
    "round": "LAST_32",
    "date": "2026-07-04T01:30:00Z",
    "homeTeam": null,
    "homeTeamName": null,
    "awayTeam": null,
    "awayTeamName": null,
    "homeGoals": null,
    "awayGoals": null,
    "status": "TIMED"
  },
  {
    "id": 537375,
    "matchday": null,
    "round": "LAST_16",
    "date": "2026-07-04T21:00:00Z",
    "homeTeam": null,
    "homeTeamName": null,
    "awayTeam": null,
    "awayTeamName": null,
    "homeGoals": null,
    "awayGoals": null,
    "status": "TIMED"
  },
  {
    "id": 537376,
    "matchday": null,
    "round": "LAST_16",
    "date": "2026-07-04T17:00:00Z",
    "homeTeam": null,
    "homeTeamName": null,
    "awayTeam": null,
    "awayTeamName": null,
    "homeGoals": null,
    "awayGoals": null,
    "status": "TIMED"
  },
  {
    "id": 537377,
    "matchday": null,
    "round": "LAST_16",
    "date": "2026-07-05T20:00:00Z",
    "homeTeam": null,
    "homeTeamName": null,
    "awayTeam": null,
    "awayTeamName": null,
    "homeGoals": null,
    "awayGoals": null,
    "status": "TIMED"
  },
  {
    "id": 537378,
    "matchday": null,
    "round": "LAST_16",
    "date": "2026-07-06T00:00:00Z",
    "homeTeam": null,
    "homeTeamName": null,
    "awayTeam": null,
    "awayTeamName": null,
    "homeGoals": null,
    "awayGoals": null,
    "status": "TIMED"
  },
  {
    "id": 537379,
    "matchday": null,
    "round": "LAST_16",
    "date": "2026-07-06T19:00:00Z",
    "homeTeam": null,
    "homeTeamName": null,
    "awayTeam": null,
    "awayTeamName": null,
    "homeGoals": null,
    "awayGoals": null,
    "status": "TIMED"
  },
  {
    "id": 537380,
    "matchday": null,
    "round": "LAST_16",
    "date": "2026-07-07T00:00:00Z",
    "homeTeam": null,
    "homeTeamName": null,
    "awayTeam": null,
    "awayTeamName": null,
    "homeGoals": null,
    "awayGoals": null,
    "status": "TIMED"
  },
  {
    "id": 537381,
    "matchday": null,
    "round": "LAST_16",
    "date": "2026-07-07T16:00:00Z",
    "homeTeam": null,
    "homeTeamName": null,
    "awayTeam": null,
    "awayTeamName": null,
    "homeGoals": null,
    "awayGoals": null,
    "status": "TIMED"
  },
  {
    "id": 537382,
    "matchday": null,
    "round": "LAST_16",
    "date": "2026-07-07T20:00:00Z",
    "homeTeam": null,
    "homeTeamName": null,
    "awayTeam": null,
    "awayTeamName": null,
    "homeGoals": null,
    "awayGoals": null,
    "status": "TIMED"
  },
  {
    "id": 537383,
    "matchday": null,
    "round": "QUARTER_FINALS",
    "date": "2026-07-09T20:00:00Z",
    "homeTeam": null,
    "homeTeamName": null,
    "awayTeam": null,
    "awayTeamName": null,
    "homeGoals": null,
    "awayGoals": null,
    "status": "TIMED"
  },
  {
    "id": 537384,
    "matchday": null,
    "round": "QUARTER_FINALS",
    "date": "2026-07-10T19:00:00Z",
    "homeTeam": null,
    "homeTeamName": null,
    "awayTeam": null,
    "awayTeamName": null,
    "homeGoals": null,
    "awayGoals": null,
    "status": "TIMED"
  },
  {
    "id": 537385,
    "matchday": null,
    "round": "QUARTER_FINALS",
    "date": "2026-07-11T21:00:00Z",
    "homeTeam": null,
    "homeTeamName": null,
    "awayTeam": null,
    "awayTeamName": null,
    "homeGoals": null,
    "awayGoals": null,
    "status": "TIMED"
  },
  {
    "id": 537386,
    "matchday": null,
    "round": "QUARTER_FINALS",
    "date": "2026-07-12T01:00:00Z",
    "homeTeam": null,
    "homeTeamName": null,
    "awayTeam": null,
    "awayTeamName": null,
    "homeGoals": null,
    "awayGoals": null,
    "status": "TIMED"
  },
  {
    "id": 537387,
    "matchday": null,
    "round": "SEMI_FINALS",
    "date": "2026-07-14T19:00:00Z",
    "homeTeam": null,
    "homeTeamName": null,
    "awayTeam": null,
    "awayTeamName": null,
    "homeGoals": null,
    "awayGoals": null,
    "status": "TIMED"
  },
  {
    "id": 537388,
    "matchday": null,
    "round": "SEMI_FINALS",
    "date": "2026-07-15T19:00:00Z",
    "homeTeam": null,
    "homeTeamName": null,
    "awayTeam": null,
    "awayTeamName": null,
    "homeGoals": null,
    "awayGoals": null,
    "status": "TIMED"
  },
  {
    "id": 537389,
    "matchday": null,
    "round": "THIRD_PLACE",
    "date": "2026-07-18T21:00:00Z",
    "homeTeam": null,
    "homeTeamName": null,
    "awayTeam": null,
    "awayTeamName": null,
    "homeGoals": null,
    "awayGoals": null,
    "status": "TIMED"
  },
  {
    "id": 537390,
    "matchday": null,
    "round": "FINAL",
    "date": "2026-07-19T19:00:00Z",
    "homeTeam": null,
    "homeTeamName": null,
    "awayTeam": null,
    "awayTeamName": null,
    "homeGoals": null,
    "awayGoals": null,
    "status": "TIMED"
  }
]